[
  {
    "thumbnail": "~url",
    "image": "/imgs/IMG_6647.jpg",
    "blockType": "6"
  },
  {
    "thumbnail": "~url",
    "image": "/imgs/IMG_6645.jpg",
    "blockType": "6"
  },
  {
    "thumbnail": "~url",
    "image": "/imgs/IMG_6641.jpg",
    "blockType": "6"
  },
  {
    "thumbnail": "~url",
    "image": "/imgs/IMG_6729.jpg",
    "blockType": "1"
  },
  {
    "thumbnail": "~url",
    "image": "/imgs/IMG_6732.jpg",
    "blockType": "1"
  },
  {
    "thumbnail": "~url",
    "image": "/imgs/IMG_6731.jpg",
    "blockType": "1"
  },
  {
    "thumbnail": "~url",
    "image": "/imgs/IMG_6734.jpg",
    "blockType": "1"
  },
  {
    "thumbnail": "~url",
    "image": "/imgs/IMG_6728.jpg",
    "blockType": "1"
  },
  {
    "thumbnail": "~url",
    "image": "/imgs/IMG_6736.jpg",
    "blockType": "6"
  },
  {
    "thumbnail": "~url",
    "image": "/imgs/IMG_6737.jpg",
    "blockType": "6"
  },
  {
    "thumbnail": "~url",
    "image": "/imgs/IMG_6743.jpg",
    "blockType": "6"
  },
  {
    "thumbnail": "~url",
    "image": "/imgs/IMG_6747.jpg",
    "blockType": "4"
  },
  {
    "thumbnail": "~url",
    "image": "/imgs/IMG_6750.jpg",
    "blockType": "4"
  },
  {
    "thumbnail": "~url",
    "image": "/imgs/IMG_6753.jpg",
    "blockType": "4"
  },
  {
    "thumbnail": "~url",
    "image": "/imgs/IMG_6755.jpg",
    "blockType": "4"
  },
  {
    "thumbnail": "~url",
    "image": "/imgs/IMG_6783.jpg",
    "blockType": "1"
  },
  {
    "thumbnail": "~url",
    "image": "/imgs/IMG_6786.jpg",
    "blockType": "1"
  },
  {
    "thumbnail": "~url",
    "image": "/imgs/IMG_6799.jpg",
    "blockType": "1"
  },
  {
    "thumbnail": "~url",
    "image": "/imgs/IMG_6791.jpg",
    "blockType": "1"
  },
  {
    "thumbnail": "~url",
    "image": "/imgs/IMG_6792.jpg",
    "blockType": "1"
  },
  {
    "thumbnail": "~url",
    "image": "/imgs/IMG_6808.jpg",
    "blockType": "4"
  },
  {
    "thumbnail": "~url",
    "image": "/imgs/IMG_6818.jpg",
    "blockType": "4"
  },
  {
    "thumbnail": "~url",
    "image": "/imgs/IMG_6817.jpg",
    "blockType": "4"
  },
  {
    "thumbnail": "~url",
    "image": "/imgs/IMG_6820.jpg",
    "blockType": "4"
  },
  {
    "thumbnail": "~url",
    "image": "/imgs/IMG_6826.jpg",
    "blockType": "2"
  },
  {
    "thumbnail": "~url",
    "image": "/imgs/IMG_6830.jpg",
    "blockType": "2"
  },
  {
    "thumbnail": "~url",
    "image": "/imgs/IMG_6892.jpg",
    "blockType": "5"
  },
  {
    "thumbnail": "~url",
    "image": "/imgs/IMG_6896.jpg",
    "blockType": "5"
  },
  {
    "thumbnail": "~url",
    "image": "/imgs/IMG_6901.jpg",
    "blockType": "5"
  },
  {
    "thumbnail": "~url",
    "image": "/imgs/IMG_6903.jpg",
    "blockType": "5"
  },
  {
    "thumbnail": "~url",
    "image": "/imgs/IMG_6906.jpg",
    "blockType": "6"
  },
  {
    "thumbnail": "~url",
    "image": "/imgs/IMG_6907.jpg",
    "blockType": "6"
  },
  {
    "thumbnail": "~url",
    "image": "/imgs/IMG_6911.jpg",
    "blockType": "6"
  },
  {
    "thumbnail": "~url",
    "image": "/imgs/IMG_6947.jpg",
    "blockType": "1"
  },
  {
    "thumbnail": "~url",
    "image": "/imgs/IMG_6927.jpg",
    "blockType": "1"
  },
  {
    "thumbnail": "~url",
    "image": "/imgs/IMG_6960.jpg",
    "blockType": "1"
  },
  {
    "thumbnail": "~url",
    "image": "/imgs/IMG_6948.jpg",
    "blockType": "1"
  },
  {
    "thumbnail": "~url",
    "image": "/imgs/IMG_6955.jpg",
    "blockType": "1"
  },
  {
    "thumbnail": "~url",
    "image": "/imgs/IMG_6944.jpg",
    "blockType": "2"
  },
  {
    "thumbnail": "~url",
    "image": "/imgs/IMG_6946.jpg",
    "blockType": "2"
  }
]
